CHANGES.txt
LICENSE.txt
setup.cfg
setup.py
zgeo.spatialindex-configure.zcml
zgeo/__init__.py
zgeo.spatialindex.egg-info/PKG-INFO
zgeo.spatialindex.egg-info/SOURCES.txt
zgeo.spatialindex.egg-info/dependency_links.txt
zgeo.spatialindex.egg-info/entry_points.txt
zgeo.spatialindex.egg-info/namespace_packages.txt
zgeo.spatialindex.egg-info/not-zip-safe
zgeo.spatialindex.egg-info/requires.txt
zgeo.spatialindex.egg-info/top_level.txt
zgeo/spatialindex/README.txt
zgeo/spatialindex/__init__.py
zgeo/spatialindex/bounds.py
zgeo/spatialindex/catalog-views.txt
zgeo/spatialindex/catalog.py
zgeo/spatialindex/configure.zcml
zgeo/spatialindex/event.py
zgeo/spatialindex/ftesting.zcml
zgeo/spatialindex/index.py
zgeo/spatialindex/interfaces.py
zgeo/spatialindex/site.py
zgeo/spatialindex/testing.py
zgeo/spatialindex/tests.py
zgeo/spatialindex/zope2.py
zgeo/spatialindex/browser/__init__.py
zgeo/spatialindex/browser/configure.zcml
zgeo/spatialindex/browser/install.pt
zgeo/spatialindex/browser/manage.py
zgeo/spatialindex/browser/manage_index_form.pt
zgeo/spatialindex/browser/query.py
zgeo/spatialindex/browser/search.pt
