Metadata-Version: 1.0
Name: zgeo.spatialindex
Version: 0.3
Summary: Spatial index for Zope
Home-page: http://trac.gispython.org/projects/PrimaGIS/wiki/zgeo.spatialindex
Author: Sean Gillies
Author-email: sgillies@frii.com
License: BSD
Keywords: gis geo spatial index
Platform: UNKNOWN
Classifier: Framework :: Plone
Classifier: Framework :: Zope3
Classifier: Programming Language :: Python
Classifier: Topic :: Software Development :: Libraries :: Python Modules
Classifier: Topic :: Scientific/Engineering :: GIS
Classifier: Development Status :: 3 - Alpha
Classifier: Intended Audience :: Developers
Classifier: License :: OSI Approved :: BSD License
